letrbinr/__init__.py
letrbinr/letrbinr.py
letrbinr-1.0.6.dist-info/licenses/LICENSE.md
letrbinr-1.0.6.dist-info/METADATA
letrbinr-1.0.6.dist-info/WHEEL
letrbinr-1.0.6.dist-info/top_level.txt
letrbinr-1.0.6.dist-info/RECORD
