Metadata-Version: 2.4
Name: letrbinr
Version: 1.0.6
Summary: A toy esoteric language
Home-page: https://github.com/Viktor640266/letrbinr
Author: Vitek
Author-email: Vitek <cheeseqwertycheese@gmail.com>
License: MIT
Project-URL: Homepage, https://github.com/Viktor640266/letrbinr
Classifier: Programming Language :: Python :: 3
Classifier: License :: OSI Approved :: MIT License
Classifier: Operating System :: OS Independent
Requires-Python: >=3.7
License-File: LICENSE.md
Dynamic: author
Dynamic: home-page
Dynamic: license-file
Dynamic: requires-python
